matspy/__init__.py
matspy/spy_renderer.py
matspy/adapters/__init__.py
matspy/adapters/graphblas_driver.py
matspy/adapters/graphblas_impl.py
matspy/adapters/numpy_driver.py
matspy/adapters/numpy_impl.py
matspy/adapters/scipy_driver.py
matspy/adapters/scipy_impl.py
matspy/adapters/sparse_driver.py
matspy/adapters/sparse_impl.py
matspy-1.0.0.dist-info/LICENSE.txt
matspy-1.0.0.dist-info/METADATA
matspy-1.0.0.dist-info/WHEEL
matspy-1.0.0.dist-info/top_level.txt
matspy-1.0.0.dist-info/RECORD
