Metadata-Version: 2.1
Name: matspy
Version: 1.0.0
Summary: Sparse matrix spy plot and sparkline renderer that works with Jupyter.
Author: Adam Lugowski
Project-URL: homepage, https://github.com/alugowski/matspy
Project-URL: repository, https://github.com/alugowski/matspy
Keywords: matrix,sparse,spy,plot,graph,numpy,scipy,graphblas
Classifier: Development Status :: 5 - Production/Stable
Classifier: Intended Audience :: Science/Research
Classifier: Intended Audience :: Developers
Classifier: License :: OSI Approved :: BSD License
Classifier: Programming Language :: Python :: 3 :: Only
Classifier: Topic :: Software Development :: Libraries
Classifier: Topic :: Scientific/Engineering
Requires-Python: >=3.7
License-File: LICENSE.txt
Requires-Dist: numpy
Requires-Dist: matplotlib
Provides-Extra: test
Requires-Dist: pytest ; extra == 'test'
Requires-Dist: scipy ; extra == 'test'
Requires-Dist: matplotlib ; extra == 'test'
Requires-Dist: html5lib ; extra == 'test'
Requires-Dist: matrepr ; extra == 'test'
Provides-Extra: testextra
Requires-Dist: python-graphblas ; extra == 'testextra'
Requires-Dist: sparse ; extra == 'testextra'
